{
  "Name": "2-BIT SUB",
  "NameLocation": 0,
  "ChipType": 0,
  "Size": {
    "x": 1.025,
    "y": 1.25
  },
  "Colour": {
    "r": 0.4348675,
    "g": 0.181765512,
    "b": 0.0548236519,
    "a": 1
  },
  "InputPins":[
    {
      "Name":"A1",
      "ID":715604280,
      "Position":{
        "x":-7.27778,
        "y":1.63889
      },
      "BitCount":1,
      "Colour":0,
      "ValueDisplayMode":0
    },
    {
      "Name":"B1",
      "ID":1806053773,
      "Position":{
        "x":-7.27778,
        "y":1.12389
      },
      "BitCount":1,
      "Colour":0,
      "ValueDisplayMode":0
    },
    {
      "Name":"BORROW IN",
      "ID":1597034752,
      "Position":{
        "x":-7.30556,
        "y":0.5463
      },
      "BitCount":1,
      "Colour":0,
      "ValueDisplayMode":0
    },
    {
      "Name":"A2",
      "ID":1361413876,
      "Position":{
        "x":-7.2963,
        "y":-0.0463
      },
      "BitCount":1,
      "Colour":0,
      "ValueDisplayMode":0
    },
    {
      "Name":"B2",
      "ID":52976153,
      "Position":{
        "x":-7.2963,
        "y":-0.5613
      },
      "BitCount":1,
      "Colour":0,
      "ValueDisplayMode":0
    }
  ],
  "OutputPins":[
    {
      "Name":"1S",
      "ID":730342831,
      "Position":{
        "x":1.55555,
        "y":1.55556
      },
      "BitCount":1,
      "Colour":0,
      "ValueDisplayMode":0
    },
    {
      "Name":"2S",
      "ID":770161604,
      "Position":{
        "x":2.69445,
        "y":0.28704
      },
      "BitCount":1,
      "Colour":0,
      "ValueDisplayMode":0
    },
    {
      "Name":"BORROW OUT",
      "ID":770333851,
      "Position":{
        "x":2.74074,
        "y":-0.37037
      },
      "BitCount":1,
      "Colour":0,
      "ValueDisplayMode":0
    }
  ],
  "SubChips":[
    {
      "Name":"FULL-SUB",
      "ID":384219022,
      "Label":"",
      "Position":{
        "x":-3.2963,
        "y":1.42593
      },
      "OutputPinColourInfo":[{"PinColour":0,"PinID":1282675746},{"PinColour":0,"PinID":1629937008}],
      "InternalData":null
    },
    {
      "Name":"FULL-SUB",
      "ID":1773574943,
      "Label":"",
      "Position":{
        "x":-1.47222,
        "y":-0.08333
      },
      "OutputPinColourInfo":[{"PinColour":0,"PinID":1282675746},{"PinColour":0,"PinID":1629937008}],
      "InternalData":null
    }
  ],
  "Wires":[
    {
      "SourcePinAddress":{
        "PinID":1282675746,
        "PinOwnerID":384219022
      },
      "TargetPinAddress":{
        "PinID":848475903,
        "PinOwnerID":1773574943
      },
      "ConnectionType":0,
      "ConnectedWireIndex":-1,
      "ConnectedWireSegmentIndex":-1,
      "Points":[{"x":0.0,"y":0.0},{"x":-2.37963,"y":1.67593},{"x":-2.37963,"y":-0.33333},{"x":0.0,"y":0.0}]
    },
    {
      "SourcePinAddress":{
        "PinID":0,
        "PinOwnerID":1597034752
      },
      "TargetPinAddress":{
        "PinID":848475903,
        "PinOwnerID":384219022
      },
      "ConnectionType":0,
      "ConnectedWireIndex":-1,
      "ConnectedWireSegmentIndex":-1,
      "Points":[{"x":0.0,"y":0.0},{"x":-4.47222,"y":0.5463},{"x":-4.47222,"y":1.17593},{"x":0.0,"y":0.0}]
    },
    {
      "SourcePinAddress":{
        "PinID":0,
        "PinOwnerID":715604280
      },
      "TargetPinAddress":{
        "PinID":458601941,
        "PinOwnerID":384219022
      },
      "ConnectionType":0,
      "ConnectedWireIndex":-1,
      "ConnectedWireSegmentIndex":-1,
      "Points":[{"x":0.0,"y":0.0},{"x":0.0,"y":0.0}]
    },
    {
      "SourcePinAddress":{
        "PinID":0,
        "PinOwnerID":1806053773
      },
      "TargetPinAddress":{
        "PinID":602801259,
        "PinOwnerID":384219022
      },
      "ConnectionType":0,
      "ConnectedWireIndex":-1,
      "ConnectedWireSegmentIndex":-1,
      "Points":[{"x":0.0,"y":0.0},{"x":-4.94444,"y":1.12389},{"x":-4.94444,"y":1.41667},{"x":0.0,"y":0.0}]
    },
    {
      "SourcePinAddress":{
        "PinID":0,
        "PinOwnerID":1361413876
      },
      "TargetPinAddress":{
        "PinID":458601941,
        "PinOwnerID":1773574943
      },
      "ConnectionType":0,
      "ConnectedWireIndex":-1,
      "ConnectedWireSegmentIndex":-1,
      "Points":[{"x":0.0,"y":0.0},{"x":-3.33333,"y":-0.0463},{"x":-3.33333,"y":0.21296},{"x":0.0,"y":0.0}]
    },
    {
      "SourcePinAddress":{
        "PinID":0,
        "PinOwnerID":52976153
      },
      "TargetPinAddress":{
        "PinID":602801259,
        "PinOwnerID":1773574943
      },
      "ConnectionType":0,
      "ConnectedWireIndex":-1,
      "ConnectedWireSegmentIndex":-1,
      "Points":[{"x":0.0,"y":0.0},{"x":-2.87963,"y":-0.5613},{"x":-2.87963,"y":-0.11111},{"x":0.0,"y":0.0}]
    },
    {
      "SourcePinAddress":{
        "PinID":1629937008,
        "PinOwnerID":1773574943
      },
      "TargetPinAddress":{
        "PinID":0,
        "PinOwnerID":770161604
      },
      "ConnectionType":0,
      "ConnectedWireIndex":-1,
      "ConnectedWireSegmentIndex":-1,
      "Points":[{"x":0.0,"y":0.0},{"x":-0.12037,"y":-0.33333},{"x":-0.12037,"y":0.28704},{"x":0.0,"y":0.0}]
    },
    {
      "SourcePinAddress":{
        "PinID":1282675746,
        "PinOwnerID":1773574943
      },
      "TargetPinAddress":{
        "PinID":0,
        "PinOwnerID":770333851
      },
      "ConnectionType":0,
      "ConnectedWireIndex":-1,
      "ConnectedWireSegmentIndex":-1,
      "Points":[{"x":0.0,"y":0.0},{"x":-0.46296,"y":0.16667},{"x":-0.35185,"y":0.16667},{"x":-0.35185,"y":-0.11111},{"x":0.19444,"y":-0.11111},{"x":0.19444,"y":-0.44444},{"x":0.0,"y":0.0}]
    },
    {
      "SourcePinAddress":{
        "PinID":1629937008,
        "PinOwnerID":384219022
      },
      "TargetPinAddress":{
        "PinID":0,
        "PinOwnerID":730342831
      },
      "ConnectionType":0,
      "ConnectedWireIndex":-1,
      "ConnectedWireSegmentIndex":-1,
      "Points":[{"x":0.0,"y":0.0},{"x":-0.56481,"y":1.17593},{"x":-0.56481,"y":1.56482},{"x":0.0,"y":0.0}]
    }
  ],
  "Displays": null
}